wordplex/__init__.py
wordplex/__main__.py
wordplex/wordplex.py
wordplex-0.2.6.dist-info/METADATA
wordplex-0.2.6.dist-info/WHEEL
wordplex-0.2.6.dist-info/RECORD
